fivana/__init__.py
fivana/cediblessdk/__init__.py
fivana/cediblessdk/classes/__init__.py
fivana/cediblessdk/classes/documentoCedible.py
fivana/cediblessdk/classes/documentoCedibleSubs.py
fivana/cediblessdk/classes/utils.py
Fivana_Cedibles_SDK-2.0.3.dist-info/METADATA
Fivana_Cedibles_SDK-2.0.3.dist-info/WHEEL
Fivana_Cedibles_SDK-2.0.3.dist-info/top_level.txt
Fivana_Cedibles_SDK-2.0.3.dist-info/RECORD
