Metadata-Version: 2.1
Name: Fivana-Cedibles-SDK
Version: 2.0.3
Summary: SDK for Cedibles documents
Home-page: https://bitbucket.org/factorclick/fc-cedibledocs-lib
Author: Reynier Lester Claro Escalona, Ernesto Herrera
Author-email: rclaro@fivana.com, eherrera@fivana.com
License: UNKNOWN
Platform: UNKNOWN
Classifier: Programming Language :: Python :: 3
Classifier: Operating System :: OS Independent
